[
    {
        "pageName" : "Boards of Canada EHX",
        "pageDescription" : "A full archive of the BOC EHX website, without the .realaudio files." ,
        "thumb" : "./ehx.png",
        "directory" : "./ehx/index.html"
    },
    {
        "pageName" : "Music Has the Right Microsite",
        "pageDescription" : "A full archive of the BOC MHTRTC Microsite website, including the .realaudio files.",
        "thumb" : "./mhtr.png",
        "directory" : "./mhtr/index.html"
    },
    {
        "pageName" : "Yesteryear",
        "pageDescription" : "My musical alias",
        "thumb" : "./yester.png",
        "directory" : "./yesteryear/index.html"
    },
    {
        "pageName" : "Chipper and Sons",
        "pageDescription" : "A HTML5 port of the classic \"Chipper and Sons\" by Scott Cawthon.",
        "thumb" : "./chipper.png",
        "directory" : "./chipper/index.html"
    },
    {
        "pageName" : "Five Nights at Chuck E Cheese's",
        "pageDescription" : "A HTML5 port of the classic Five Nights at Freddy's fangame \"Five Nights at Chuck E Cheese's\" by jollytea.",
        "thumb" : "./fnacec.png",
        "directory" : "./fnacec/index.html"
    }
]